univariate/__init__.py
univariate/univariate_analyzer.py
univariate/analyzer/__init__.py
univariate/analyzer/analysis_report.py
univariate/analyzer/analyzer.py
univariate/analyzer/autocorrelation_analyzer.py
univariate/analyzer/decomposition_analyzer.py
univariate/analyzer/descriptive_stat_analyzer.py
univariate/analyzer/regularity_analyzer.py
univariate/anomaly/__init__.py
univariate/anomaly/detector/__init__.py
univariate/anomaly/detector/anomaly_detector.py
univariate/anomaly/detector/iqr_outlier_detector.py
univariate/anomaly/detector/residual_anomaly_detector.py
univariate/anomaly/handling/__init__.py
univariate/anomaly/handling/anomaly_handler.py
univariate/anomaly/handling/strategy/__init__.py
univariate/anomaly/handling/strategy/anomaly_handling_strategy.py
univariate/anomaly/handling/strategy/exponential_moving_average.py
univariate/duplicate/__init__.py
univariate/duplicate/duplicate_processor.py
univariate/duplicate/duplicate_report.py
univariate/hook/__init__.py
univariate/hook/hook.py
univariate/hook/stdout_hook.py
univariate/missing_value/__init__.py
univariate/missing_value/missing_value_detector.py
univariate/missing_value/missing_value_report.py
univariate/missing_value/handler/__init__.py
univariate/missing_value/handler/missing_value_handler.py
univariate/missing_value/handler/strategy/__init__.py
univariate/missing_value/handler/strategy/bocf_imputation.py
univariate/missing_value/handler/strategy/cubic_spline_interpolation.py
univariate/missing_value/handler/strategy/deletion.py
univariate/missing_value/handler/strategy/lagrange_interpolation.py
univariate/missing_value/handler/strategy/linear_interploation.py
univariate/missing_value/handler/strategy/locf_imputation.py
univariate/missing_value/handler/strategy/mean_imputation.py
univariate/missing_value/handler/strategy/median_imputation.py
univariate/missing_value/handler/strategy/missing_value_handle_strategy.py
univariate/missing_value/handler/strategy/mode_imputation.py
aicns_univariate_analyzer-0.16.0.dist-info/LICENSE
aicns_univariate_analyzer-0.16.0.dist-info/METADATA
aicns_univariate_analyzer-0.16.0.dist-info/WHEEL
aicns_univariate_analyzer-0.16.0.dist-info/top_level.txt
aicns_univariate_analyzer-0.16.0.dist-info/RECORD
