Metadata-Version: 2.1
Name: aicns-univariate-analyzer
Version: 0.16.0
Summary: Univariate time series analyzer library package in AICNS project
Home-page: UNKNOWN
Author: Youngmin An
Author-email: youngmin.develop@gmail.com
License: Apache License 2.0
Platform: UNKNOWN
License-File: LICENSE
Requires-Dist: pandas (==1.1.5)
Requires-Dist: plotly (==5.10.0)
Requires-Dist: pyspark (>=3.1.0)
Requires-Dist: scikit-learn (==0.24.2)
Requires-Dist: statsmodels (==0.13.2)
Requires-Dist: pendulum (==2.1.2)
